stratigrapy/__init__.py
stratigrapy/utils.py
stratigrapy/components/__init__.py
stratigrapy/components/_base.py
stratigrapy/components/compaction/__init__.py
stratigrapy/components/compaction/sediment_compactor.py
stratigrapy/components/diffusion/__init__.py
stratigrapy/components/diffusion/cfuncs.cpython-311-aarch64-linux-gnu.so
stratigrapy/components/diffusion/cfuncs.pyx
stratigrapy/components/diffusion/gravity_driven_diffuser.py
stratigrapy/components/diffusion/gravity_driven_router.py
stratigrapy/components/landsliding/__init__.py
stratigrapy/components/landsliding/cfuncs.cpython-311-aarch64-linux-gnu.so
stratigrapy/components/landsliding/cfuncs.pyx
stratigrapy/components/landsliding/simple_sediment_landslider.py
stratigrapy/components/sea_level/__init__.py
stratigrapy/components/sea_level/cyclic_sea_level_calculator.py
stratigrapy/components/sea_level/sea_level_calculator.py
stratigrapy/components/source/__init__.py
stratigrapy/components/source/source_producer.py
stratigrapy/components/stream_power/__init__.py
stratigrapy/components/stream_power/cfuncs.cpython-311-aarch64-linux-gnu.so
stratigrapy/components/stream_power/cfuncs.pyx
stratigrapy/components/stream_power/flux_driven_router.py
stratigrapy/components/stream_power/water_driven_diffuser.py
stratigrapy/components/stream_power/water_driven_router.py
stratigrapy/components/weathering/__init__.py
stratigrapy/components/weathering/bedrock_weatherer.py
stratigrapy/grid/__init__.py
stratigrapy/grid/cfuncs.cpython-311-aarch64-linux-gnu.so
stratigrapy/grid/cfuncs.pyx
stratigrapy/grid/divergence.py
stratigrapy/grid/grids.py
stratigrapy/grid/raster_divergence.py
stratigrapy/layers/__init__.py
stratigrapy/layers/cfuncs.cpython-311-aarch64-linux-gnu.so
stratigrapy/layers/cfuncs.pyx
stratigrapy/layers/stackedlayers.py
stratigrapy/plot/__init__.py
stratigrapy/plot/cfuncs.cpython-311-aarch64-linux-gnu.so
stratigrapy/plot/cfuncs.pyx
stratigrapy/plot/layers.py
stratigrapy-0.0.2.dist-info/METADATA
stratigrapy-0.0.2.dist-info/WHEEL
stratigrapy-0.0.2.dist-info/top_level.txt
stratigrapy-0.0.2.dist-info/RECORD
stratigrapy-0.0.2.dist-info/licenses/LICENSE
