Metadata-Version: 2.4
Name: stratigrapy
Version: 0.0.2
Summary: Python package for stratigraphic modeling based on Landlab
Author: Guillaume Rongier
License-Expression: MIT
Project-URL: Homepage, https://github.com/grongier/stratigrapy
Project-URL: Bug Tracker, https://github.com/grongier/stratigrapy/issues
Keywords: python,stratigraphy,sedimentology,stratigraphic modeling,basin modeling
Classifier: Intended Audience :: Science/Research
Classifier: Topic :: Scientific/Engineering
Classifier: Development Status :: 4 - Beta
Classifier: Natural Language :: English
Classifier: Programming Language :: Python :: 3.10
Classifier: Programming Language :: Python :: 3.11
Classifier: Programming Language :: Python :: 3.12
Classifier: Programming Language :: Python :: 3.13
Classifier: Operating System :: OS Independent
Requires-Python: >=3.10
License-File: LICENSE
Requires-Dist: numpy
Requires-Dist: landlab
Dynamic: license-file
